kafe/__init__.py
kafe/_version_info.py
kafe/config.py
kafe/dataset.py
kafe/dataset_tools.py
kafe/file_tools.py
kafe/fit.py
kafe/function_library.py
kafe/function_tools.py
kafe/iminuit_wrapper.py
kafe/latex_tools.py
kafe/minuit.py
kafe/multifit.py
kafe/multiplot.py
kafe/numeric_tools.py
kafe/plot.py
kafe/stream.py
kafe/config/kafe.default.conf
kafe-1.3.3.dist-info/AUTHORS
kafe-1.3.3.dist-info/LICENSE
kafe-1.3.3.dist-info/METADATA
kafe-1.3.3.dist-info/WHEEL
kafe-1.3.3.dist-info/top_level.txt
kafe-1.3.3.dist-info/RECORD
