Metadata-Version: 2.1
Name: kafe
Version: 1.3.3
Summary: A Python Package for Introduction to         Data Analysis in Physics Lab Courses
Home-page: https://github.com/dsavoiu/kafe
Author: Daniel Savoiu, Guenter Quast, Joerg Schindler
Author-email: daniel.savoiu@cern.ch
License: GNU Public Licence v3
Keywords: data analysis lab courses education students physics fitting minimization
Platform: UNKNOWN
Classifier: Development Status :: 5 - Production/Stable
Classifier: Intended Audience :: Education
Classifier: Intended Audience :: Science/Research
Classifier: Topic :: Education
Classifier: Topic :: Scientific/Engineering
Classifier: Topic :: Scientific/Engineering :: Physics
Classifier: Topic :: Scientific/Engineering :: Information Analysis
Classifier: Topic :: Scientific/Engineering :: Visualization
Classifier: License :: OSI Approved :: GNU General Public License v3 (GPLv3)
Classifier: Programming Language :: Python :: 2
Classifier: Programming Language :: Python :: 2.7
